noisy_cifar/CIFAR-N.zip
noisy_cifar/__init__.py
noisy_cifar/datasets.py
noisy_cifar/utils.py
noisy_cifar_owaix2quzq-0.0.1.dist-info/LICENSE
noisy_cifar_owaix2quzq-0.0.1.dist-info/METADATA
noisy_cifar_owaix2quzq-0.0.1.dist-info/WHEEL
noisy_cifar_owaix2quzq-0.0.1.dist-info/top_level.txt
noisy_cifar_owaix2quzq-0.0.1.dist-info/RECORD
