Metadata-Version: 2.1
Name: noisy-cifar-owaix2quzq
Version: 0.0.1
Summary: CIFAR datasets with label noise
Home-page: https://github.com/Holim0711/NoisyCIFAR
Author: Holim Lim
Author-email: ihl7029@europa.snu.ac.kr
Classifier: Programming Language :: Python :: 3
Classifier: License :: OSI Approved :: MIT License
Classifier: Operating System :: OS Independent
Requires-Python: >=3.8
License-File: LICENSE
